cdk8s_kuma_types/__init__.py
cdk8s_kuma_types/py.typed
cdk8s_kuma_types/_jsii/__init__.py
cdk8s_kuma_types/_jsii/cdk8s-kuma-types@0.0.12.jsii.tgz
cdk8s_kuma_types-0.0.12.dist-info/LICENSE
cdk8s_kuma_types-0.0.12.dist-info/METADATA
cdk8s_kuma_types-0.0.12.dist-info/WHEEL
cdk8s_kuma_types-0.0.12.dist-info/top_level.txt
cdk8s_kuma_types-0.0.12.dist-info/RECORD
